nexus_flow/__init__.py
nexus_flow/framework/__init__.py
nexus_flow/framework/doc_item_commiter.py
nexus_flow/github/__init__.py
nexus_flow/github/github_client_service.py
nexus_flow/hash/__init__.py
nexus_flow/hash/hash_info.py
nexus_flow/hash/hash_utils.py
nexus_flow/hi_service.py
nexus_flow/infra/__init__.py
nexus_flow/infra/nexus_flow_constant.py
nexus_flow/nexus_flow_app.py
nexus_flow/s3/__init__.py
nexus_flow/s3/s3_service.py
nexus_flow-0.1.12.dist-info/LICENSE
nexus_flow-0.1.12.dist-info/METADATA
nexus_flow-0.1.12.dist-info/WHEEL
nexus_flow-0.1.12.dist-info/RECORD
