Metadata-Version: 2.1
Name: nexus-flow
Version: 0.1.12
Summary: 
Author: kirin
Author-email: kirin.chen1001@gmail.com
Requires-Python: >=3.11,<4.0
Classifier: Programming Language :: Python :: 3
Classifier: Programming Language :: Python :: 3.11
Classifier: Programming Language :: Python :: 3.12
Requires-Dist: boto3 (>=1.35.95,<2.0.0)
Requires-Dist: py-common-utility (>=0.1.4,<0.2.0)
Requires-Dist: pygithub (>=2.5.0,<3.0.0)
Requires-Dist: requests (>=2.32.3,<3.0.0)
